docstub/__init__.py
docstub/__main__.py
docstub/_analysis.py
docstub/_app_generate_stubs.py
docstub/_cache.py
docstub/_cli.py
docstub/_cli_help.py
docstub/_concurrency.py
docstub/_config.py
docstub/_docstrings.py
docstub/_path_utils.py
docstub/_report.py
docstub/_stubs.py
docstub/_utils.py
docstub/_version.py
docstub/_version.pyi
docstub/config_template.toml
docstub/doctype.lark
docstub/numpy_config.toml
docstub/_vendored/__init__.py
docstub/_vendored/stdlib.py
docstub-0.6.0.dist-info/licenses/LICENSE.txt
docstub-stubs/__init__.pyi
docstub-stubs/__main__.pyi
docstub-stubs/_analysis.pyi
docstub-stubs/_app_generate_stubs.pyi
docstub-stubs/_cache.pyi
docstub-stubs/_cli.pyi
docstub-stubs/_cli_help.pyi
docstub-stubs/_concurrency.pyi
docstub-stubs/_config.pyi
docstub-stubs/_docstrings.pyi
docstub-stubs/_path_utils.pyi
docstub-stubs/_report.pyi
docstub-stubs/_stubs.pyi
docstub-stubs/_utils.pyi
docstub-stubs/_version.pyi
docstub-stubs/py.typed
docstub-stubs/_vendored/__init__.pyi
docstub-stubs/_vendored/stdlib.pyi
docstub-0.6.0.dist-info/METADATA
docstub-0.6.0.dist-info/WHEEL
docstub-0.6.0.dist-info/entry_points.txt
docstub-0.6.0.dist-info/top_level.txt
docstub-0.6.0.dist-info/RECORD
