Metadata-Version: 2.4
Name: docstub
Version: 0.6.0
Summary: Generate Python stub files from docstrings
Maintainer: Lars Grüter
License-Expression: BSD-3-Clause AND PSF-2.0
Project-URL: Homepage, https://github.com/lagru/docstub
Keywords: typing,stub files,docstings,numpydoc
Classifier: Development Status :: 3 - Alpha
Classifier: Environment :: Console
Classifier: Intended Audience :: Developers
Classifier: Intended Audience :: Science/Research
Classifier: Operating System :: OS Independent
Classifier: Programming Language :: Python
Classifier: Programming Language :: Python :: 3
Classifier: Programming Language :: Python :: 3 :: Only
Classifier: Programming Language :: Python :: 3.12
Classifier: Programming Language :: Python :: 3.13
Classifier: Programming Language :: Python :: 3.14
Classifier: Topic :: Software Development :: Code Generators
Classifier: Topic :: Scientific/Engineering
Requires-Python: >=3.12
License-File: LICENSE.txt
Requires-Dist: numpydoc>=1.7.0
Requires-Dist: click>=8.1.7
Requires-Dist: libcst>=1.3.1
Requires-Dist: lark>=1.1.9
Requires-Dist: black>=24.4.2
Requires-Dist: isort>=5.13.2
Dynamic: license-file
